new.v
module fa(output S,O, input A,B,C);
  wire t1,t2,t3;
  and(t1,A,B),(t2,B,C),(t3,A,C);
  xor(S,A,B,C);
  or(O,t1,t2,t3);
endmodule

module new;
  reg A,B,C;
  wire S,O;
  fa instance0(S,O,A,B,C);
  initial begin
    $dumpfile("fulladder.vcd");
    $dumpvars(1);
    $display("Full Adder \nA B C     S O");
    $monitor(A," ", B, " ", C, "     ",S," ",O);
    A=0;B=0;C=0;
    #1; A=0;B=0;C=1;
    #1; A=0;B=1;C=0;
    #1; A=0;B=1;C=1;
    #1; A=1;B=0;C=0;
    #1; A=1;B=0;C=1;
    #1; A=1;B=1;C=0;
    #1; A=1;B=1;C=1;
    #1;
  end 
endmodule

fulladder.vcd
$date
	Wed Aug 16 08:48:34 2023
$end
$version
	Icarus Verilog
$end
$timescale
	1s
$end
$scope module new $end
$var wire 1 ! S $end
$var wire 1 " O $end
$var reg 1 # A $end
$var reg 1 $ B $end
$var reg 1 % C $end
$upscope $end
$enddefinitions $end
$comment Show the parameter values. $end
$dumpall
$end
#0
$dumpvars
0%
0$
0#
0"
0!
$end
#1
1!
1%
#2
0%
1$
#3
1"
0!
1%
#4
0"
1!
0%
0$
1#
#5
1"
0!
1%
#6
0%
1$
#7
1!
1%
