binary_to_grey.v


module bin2gre(output [3:0]g, input [3:0]b);
 assign g[3]=b[3];
 xor(g[2],b[3],b[2]),(g[1],b[1],b[2]),(g[0],b[1],b[0]);
endmodule

module binary_to_grey;
 reg [3:0]b;
 wire [3:0]g;
 bin2gre instance0(g,b);
 initial begin
    $dumpfile("hel.vcd");
    $dumpvars(1);
    $display(" Binary to grey");
    $monitor(" %b  %b",b,g);

    b=0;
    #1;b=1;
    #1;b=2;
    #1;b=3;
    #1;b=4;
    #1;b=5;
    #1;b=6;
    #1;b=7;
    #1;b=8;
    #1;b=9;
    #1;b=10;
    #1;b=11;
    #1;b=12;
    #1;b=13;
    #1;b=14;
    #1;b=15;
    #1;
 end
endmodule

hel.vcd
$date
	Wed Aug 16 10:09:38 2023
$end
$version
	Icarus Verilog
$end
$timescale
	1s
$end
$scope module binary_to_grey $end
$var wire 4 ! g [3:0] $end
$var reg 4 " b [3:0] $end
$upscope $end
$enddefinitions $end
$comment Show the parameter values. $end
$dumpall
$end
#0
$dumpvars
b0 "
b0 !
$end
#1
b1 !
b1 "
#2
b11 !
b10 "
#3
b10 !
b11 "
#4
b110 !
b100 "
#5
b111 !
b101 "
#6
b101 !
b110 "
#7
b100 !
b111 "
#8
b1100 !
b1000 "
#9
b1101 !
b1001 "
#10
b1111 !
b1010 "
#11
b1110 !
b1011 "
#12
b1010 !
b1100 "
#13
b1011 !
b1101 "
#14
b1001 !
b1110 "
#15
b1000 !
b1111 "
