main.v
module fun(output x,y,input a,b,c);
 wire t1,t2,t3;
 and(t1,a,b),(t2,b,c),(t3,c,a);
 xor(x,a,b,c);
 or(y,t1,t2,t3);
endmodule

module main;
 reg a,b,c;
 wire x,y;
 fun instance0(x,y,a,b,c);
 initial begin
  $dumpfile("outp.vcd");
  $dumpvars(1);
  $display("Function\n a b c   s  c");
  $monitor(a," ",b," ",c,"  ",x,"  ",y);
  a=0;b=0;c=0;
  #1; a=0;b=0;;c=1;
  #1; a=0;b=1;c=0;
  #1; a=0;b=1;c=1;
  #1; a=1;b=0;c=0;
  #1; a=1;b=0;c=1;
  #1; a=1;b=1;c=0;
  #1; a=1;b=1;c=1;
  #1;
 end
endmodule

outp.vcd
$date
	Wed Aug 16 07:27:38 2023
$end
$version
	Icarus Verilog
$end
$timescale
	1s
$end
$scope module main $end
$var wire 1 ! y $end
$var wire 1 " x $end
$var reg 1 # a $end
$var reg 1 $ b $end
$var reg 1 % c $end
$upscope $end
$enddefinitions $end
$comment Show the parameter values. $end
$dumpall
$end
#0
$dumpvars
0%
0$
0#
0"
0!
$end
#1
1"
1%
#2
0%
1$
#3
1!
0"
1%
#4
0!
1"
0%
0$
1#
#5
1!
0"
1%
#6
0%
1$
#7
1"
1%
